hcaptcha_solver/__init__.py
hcaptcha_solver/hcaptcha_solver.py
hcaptcha_solver/model_handler.py
hcaptcha_solver/models/bonsai tree
hcaptcha_solver/models/car
hcaptcha_solver/models/cup of orange juice
hcaptcha_solver/models/flower
hcaptcha_solver/models/headphones
hcaptcha_solver/models/helicopter
hcaptcha_solver/models/laptop
hcaptcha_solver/models/motorcycle
hcaptcha_solver/models/tree
hcaptcha_solver/models/violin
hcaptcha_solver/webdriver_handler.py
hcaptcha_solver-0.2.14.dist-info/METADATA
hcaptcha_solver-0.2.14.dist-info/WHEEL
hcaptcha_solver-0.2.14.dist-info/RECORD
