Metadata-Version: 2.1
Name: hcaptcha-solver
Version: 0.2.14
Summary: A lightweight python library for solving hCaptcha challenges with selenium.
Author: xTerradon
Requires-Python: >=3.7,<4.0
Classifier: Development Status :: 3 - Alpha
Classifier: License :: OSI Approved :: MIT License
Classifier: Operating System :: OS Independent
Classifier: Programming Language :: Python :: 3
Classifier: Programming Language :: Python :: 3.7
Classifier: Programming Language :: Python :: 3.8
Classifier: Programming Language :: Python :: 3.9
Classifier: Programming Language :: Python :: 3.10
Classifier: Programming Language :: Python :: 3.11
Requires-Dist: matplotlib
Requires-Dist: numpy
Requires-Dist: pillow
Requires-Dist: requests
Requires-Dist: selenium
Requires-Dist: torch
Requires-Dist: unidecode
Project-URL: Homepage, https://github.com/xTerradon/hcaptcha-solver
